CONTRIBUTING.md
LICENSE
MANIFEST.in
README.md
setup.py
bletchley/__init__.py
bletchley/frequencies.json
bletchley/indicies_of_coincidence.json
bletchley.egg-info/PKG-INFO
bletchley.egg-info/SOURCES.txt
bletchley.egg-info/dependency_links.txt
bletchley.egg-info/not-zip-safe
bletchley.egg-info/requires.txt
bletchley.egg-info/top_level.txt
bletchley/ciphers/__init__.py
bletchley/ciphers/adfgvx_cipher.py
bletchley/ciphers/adfgx_cipher.py
bletchley/ciphers/atbash_cipher.py
bletchley/ciphers/caesar_cipher.py
bletchley/ciphers/cipher.py
bletchley/ciphers/playfair_cipher.py
bletchley/ciphers/rot13_cipher.py
bletchley/ciphers/vic_cipher.py
bletchley/ciphers/vigenere_cipher.py
bletchley/cryptanalysis/__init__.py
bletchley/cryptanalysis/frequency_analysis.py
bletchley/cryptanalysis/index_of_coincidence.py
bletchley/cryptanalysis/kasiski_examination.py
test/__init__.py
test/ciphers/ test_adfgvx_cipher.py
test/ciphers/__init__.py
test/ciphers/test_adfgx_cipher.py
test/ciphers/test_atbash_cipher.py
test/ciphers/test_caesar_cipher.py
test/ciphers/test_cipher.py
test/ciphers/test_rot13.py
test/ciphers/test_vic_cipher.py
test/ciphers/test_vigenere_cipher.py
test/cryptanalysis/__init__.py
test/cryptanalysis/test_frequency_analysis.py
test/tutorials/__init__.py
test/tutorials/test_cipher_tutorials.py