Metadata-Version: 2.1
Name: bletchley
Version: 0.3.0
Summary: A collection of historical ciphers and cryptanalysis tools
Home-page: https://gitlab.com/manny_cyber_wizard/bletchley
Author: manny
Author-email: manny@cyber-wizard.com
License: GPL version 3
Project-URL: Bug Reports, https://gitlab.com/manny_cyber_wizard/bletchley/issues
Project-URL: Say Thanks!, https://saythanks.io/to/MannyCyber
Project-URL: Source, https://gitlab.com/manny_cyber_wizard/bletchley
Keywords: cryptography ciphers cryptanalysis historical
Platform: UNKNOWN
Classifier: Programming Language :: Python :: 3
Classifier: Programming Language :: Python :: 3 :: Only
Classifier: Programming Language :: Python :: 3.6
Classifier: Programming Language :: Python :: 3.7
Classifier: Programming Language :: Python :: 3.8
Classifier: License :: OSI Approved :: GNU General Public License v3 (GPLv3)
Classifier: Operating System :: OS Independent
Classifier: Topic :: Security :: Cryptography
Classifier: Development Status :: 3 - Alpha
